{
    "rdf_content": {
        "authors": [
            {
                "affiliation": "MRC LMB",
                "github_user": "danifranco",
                "name": "Daniel Franco-Barranco",
                "orcid": "0000-0002-1109-110X"
            }
        ],
        "cite": [
            {
                "doi": "10.1038/s41592-022-01639-4",
                "text": "Cutler, Kevin J., et al. 'Omnipose: a high-precision morphology-independent solution for bacterial cell segmentation.' Nature methods 19.11 (2022): 1438-1448.",
                "url": "https://osf.io/xmury/overview"
            }
        ],
        "covers": [
            "omnipose.png"
        ],
        "description": "The Omnipose (bact_phase) dataset is a large-scale collection of bacterial phase-contrast micrographs designed for training and benchmarking cell segmentation algorithms. It comprises 4,833 images capturing approximately 700,900 individual bacterial cells from 14 species, encompassing a wide diversity of cell morphologies and optical characteristics. \nManual cell annotation was performed using a streamlined labeling process, resulting in 47,000 accurately annotated cells that serve as the ground-truth segmentation dataset. These annotations were divided into a training set (27,500 cells) and a benchmarking set (19,500 cells), with comparable distributions of cellular metrics such as area, perimeter, and mean diameter, ensuring that the benchmarking subset faithfully represents the training data.",
        "documentation": "Omnipose.md",
        "format_version": "0.3.0",
        "id": "frosty-honey",
        "id_emoji": "🍯",
        "license": "CC-BY-NC-3.0",
        "name": "Omnipose",
        "source": "https://osf.io/xmury/overview",
        "tags": [
            "instance-segmentation",
            "2D",
            "cell",
            "bacteria",
            "phase-contrast"
        ],
        "type": "dataset",
        "uploader": {
            "email": "danialtza@gmail.com",
            "name": "Daniel Franco-Barranco"
        },
        "version": "0.1.0"
    },
    "rdf_yaml_sha256": "24129933ca1421116c1317e1a09a9da1a5d7823a75a153712b11c0d8f2dcc0b3",
    "scores": {
        "core_compatibility": 0.5,
        "metadata_completeness": 0.6296296296296297,
        "metadata_format": 1.0,
        "overall_compatibility": 0.5324074074074074,
        "overall_partner_tool_compatibility": 0.0,
        "tool_compatibility": {
            "bioimageio.core": 0.5
        },
        "tool_compatibility_version_specific": {
            "bioimageio.core_0.9.5": 0.5
        }
    },
    "status": "passed",
    "tests": {
        "bioimageio.core": {
            "0.9.5": {
                "badge": null,
                "details": {
                    "details": [
                        {
                            "context": {
                                "file_name": "rdf.yaml",
                                "known_files": {
                                    "https://hypha.aicell.io/bioimage-io/artifacts/frosty-honey/files/Omnipose.md?version=v0": null,
                                    "https://hypha.aicell.io/bioimage-io/artifacts/frosty-honey/files/omnipose.png?version=v0": null,
                                    "https://osf.io/xmury/overview": null
                                },
                                "original_source_name": null,
                                "perform_io_checks": true,
                                "root": "https://hypha.aicell.io/bioimage-io/artifacts/frosty-honey/files?version=v0",
                                "update_hashes": false
                            },
                            "errors": [],
                            "loc": [],
                            "name": "Successfully created `DatasetDescr` instance.",
                            "recommended_env": null,
                            "saved_conda_compare": null,
                            "status": "passed",
                            "warnings": []
                        },
                        {
                            "context": null,
                            "errors": [],
                            "loc": [],
                            "name": "bioimageio.spec format validation dataset 0.3.0",
                            "recommended_env": null,
                            "saved_conda_compare": null,
                            "status": "passed",
                            "warnings": [
                                {
                                    "loc": [
                                        "description"
                                    ],
                                    "msg": "Description longer than 512 characters.",
                                    "severity": 30,
                                    "type": "warning"
                                }
                            ]
                        }
                    ],
                    "env": [
                        [
                            "bioimageio.spec",
                            "0.5.6.0",
                            "",
                            ""
                        ]
                    ],
                    "format_version": "0.3.0",
                    "id": "frosty-honey",
                    "metadata_completeness": 0.6296296296296297,
                    "name": "bioimageio format validation",
                    "saved_conda_list": "# packages in environment at /usr/share/miniconda/envs/core:\n#\n# Name                     Version          Build            Channel\n",
                    "source_name": "https://hypha.aicell.io/bioimage-io/artifacts/frosty-honey/files/rdf.yaml?version=v0",
                    "status": "valid-format",
                    "traceback": null,
                    "type": "dataset",
                    "warnings": null
                },
                "error": "",
                "links": [],
                "score": 0.5,
                "status": "failed"
            }
        }
    }
}