{
    "badge": null,
    "details": {
        "conda_list": null,
        "details": [
            {
                "conda_compare": null,
                "context": {
                    "file_name": "rdf.yaml",
                    "known_files": {
                        "model.py": "67c4280cdbd1d815888b9247d80b0af9ad8f525d6b5c802797a908e795db93fc",
                        "sample_input.tif": "dc47897c483e5ba42965b00171cbf5b96de33c4bf46b0521cb888358657c8f37",
                        "sample_output.tif": "15eb3df516c6c7dd06b23f11f4b0ea5479c342d9fb9a88c870e0e75f48103733",
                        "test_input.npy": "39d9cb7a8aeca76e4c915ab21b3ef317429dba81b8fef601fe7a0b18f1338538",
                        "test_output.npy": "5c31cdd9d99e67fd10f9d387b4315dc978257c8805e2c8300621212b4a122ef7",
                        "weights.onnx": "55ad061651840fe4b6da6733c52402ae3296392f74fed8a9482e4bc62040938f",
                        "weights.pt": "461f1151d7fea5857ce8f9ceaf9cdf08b5f78ce41785725e39a77d154ccea90a",
                        "weights_torchscript.pt": "ec01e0c212b5eb422dda208af004665799637a2f2729d0ebf2e884e5d9966fc2"
                    },
                    "perform_io_checks": true,
                    "root": "https://hypha.aicell.io/bioimage-io/artifacts/ambitious-sloth/files?version=v0",
                    "update_hashes": false
                },
                "errors": [],
                "loc": [],
                "name": "Created `InvalidDescr` object.",
                "recommended_env": null,
                "status": "failed",
                "warnings": []
            },
            {
                "conda_compare": null,
                "context": {
                    "file_name": "rdf.yaml",
                    "known_files": {
                        "model.py": "67c4280cdbd1d815888b9247d80b0af9ad8f525d6b5c802797a908e795db93fc",
                        "sample_input.tif": "dc47897c483e5ba42965b00171cbf5b96de33c4bf46b0521cb888358657c8f37",
                        "sample_output.tif": "15eb3df516c6c7dd06b23f11f4b0ea5479c342d9fb9a88c870e0e75f48103733",
                        "test_input.npy": "39d9cb7a8aeca76e4c915ab21b3ef317429dba81b8fef601fe7a0b18f1338538",
                        "test_output.npy": "5c31cdd9d99e67fd10f9d387b4315dc978257c8805e2c8300621212b4a122ef7",
                        "weights.onnx": "55ad061651840fe4b6da6733c52402ae3296392f74fed8a9482e4bc62040938f",
                        "weights.pt": "461f1151d7fea5857ce8f9ceaf9cdf08b5f78ce41785725e39a77d154ccea90a",
                        "weights_torchscript.pt": "ec01e0c212b5eb422dda208af004665799637a2f2729d0ebf2e884e5d9966fc2"
                    },
                    "perform_io_checks": true,
                    "root": "https://hypha.aicell.io/bioimage-io/artifacts/ambitious-sloth/files?version=v0",
                    "update_hashes": false
                },
                "errors": [
                    {
                        "loc": [
                            "inputs",
                            0
                        ],
                        "msg": "Value error, <COMPRESSION.ADOBE_DEFLATE: 8> requires the 'imagecodecs' package",
                        "traceback_html": "",
                        "traceback_md": "",
                        "type": "value_error",
                        "with_traceback": false
                    }
                ],
                "loc": [],
                "name": "bioimageio.spec format validation model 0.5.4",
                "recommended_env": null,
                "status": "failed",
                "warnings": []
            },
            {
                "conda_compare": null,
                "context": null,
                "errors": [],
                "loc": [
                    "type"
                ],
                "name": "Has expected resource type",
                "recommended_env": null,
                "status": "passed",
                "warnings": []
            }
        ],
        "env": [
            [
                "bioimageio.core",
                "0.8.0",
                "",
                ""
            ],
            [
                "bioimageio.spec",
                "0.5.4.1",
                "",
                ""
            ]
        ],
        "format_version": "0.5.4",
        "id": "ambitious-sloth",
        "name": "bioimageio format validation",
        "source_name": "https://hypha.aicell.io/bioimage-io/artifacts/ambitious-sloth/files/rdf.yaml?version=v0",
        "status": "failed",
        "type": "model"
    },
    "error": "\n|        ❌        |                               bioimageio format validation                              |\n|       ---       |                                           ---                                           |\n| status          | failed                                                                                  |\n| source          | https://hypha.aicell.io/bioimage-io/artifacts/ambitious-sloth/files/rdf.yaml?version=v0 |\n| id              | ambitious-sloth                                                                         |\n| format version  | model 0.5.4                                                                             |\n| bioimageio.core | 0.8.0                                                                                   |\n| bioimageio.spec | 0.5.4.1                                                                                 |\n\n|     |                   Location                   |                                    Details                                     |\n| --- |                     ---                      |                                      ---                                       |\n| ❌   |                                              | Created `InvalidDescr` object.                                                 |\n| 🔍   | `context:perform_io_checks`                  | True                                                                           |\n| 🔍   | `context:root`                               | https://hypha.aicell.io/bioimage-io/artifacts/ambitious-sloth/files?version=v0 |\n| 🔍   | `context:known_files.test_input.npy`         | 39d9cb7a8aeca76e4c915ab21b3ef317429dba81b8fef601fe7a0b18f1338538               |\n| 🔍   | `context:known_files.sample_input.tif`       | dc47897c483e5ba42965b00171cbf5b96de33c4bf46b0521cb888358657c8f37               |\n| 🔍   | `context:known_files.test_output.npy`        | 5c31cdd9d99e67fd10f9d387b4315dc978257c8805e2c8300621212b4a122ef7               |\n| 🔍   | `context:known_files.sample_output.tif`      | 15eb3df516c6c7dd06b23f11f4b0ea5479c342d9fb9a88c870e0e75f48103733               |\n| 🔍   | `context:known_files.weights.onnx`           | 55ad061651840fe4b6da6733c52402ae3296392f74fed8a9482e4bc62040938f               |\n| 🔍   | `context:known_files.model.py`               | 67c4280cdbd1d815888b9247d80b0af9ad8f525d6b5c802797a908e795db93fc               |\n| 🔍   | `context:known_files.weights.pt`             | 461f1151d7fea5857ce8f9ceaf9cdf08b5f78ce41785725e39a77d154ccea90a               |\n| 🔍   | `context:known_files.weights_torchscript.pt` | ec01e0c212b5eb422dda208af004665799637a2f2729d0ebf2e884e5d9966fc2               |\n| ❌   |                                              | bioimageio.spec format validation model 0.5.4                                  |\n| ❌   | `inputs.0`                                   | Value error, <COMPRESSION.ADOBE_DEFLATE: 8> requires the 'imagecodecs' package |\n|     |                                              |                                                                                |\n| ✔️  | `type`                                       | Has expected resource type                                                     |\n",
    "links": [
        "ilastik/ilastik"
    ],
    "status": "failed",
    "tool": "ilastik"
}